sklvq/__init__.py
sklvq/_utils.py
sklvq/_version.py
sklvq/activations/__init__.py
sklvq/activations/_base.py
sklvq/activations/_identity.py
sklvq/activations/_sigmoid.py
sklvq/activations/_soft_plus.py
sklvq/activations/_swish.py
sklvq/activations/tests/__init__.py
sklvq/activations/tests/test_common.py
sklvq/activations/tests/test_identity.py
sklvq/activations/tests/test_sigmoid.py
sklvq/activations/tests/test_soft_plus.py
sklvq/activations/tests/test_swish.py
sklvq/discriminants/__init__.py
sklvq/discriminants/_base.py
sklvq/discriminants/_relative_distance.py
sklvq/discriminants/tests/__init__.py
sklvq/discriminants/tests/test_common.py
sklvq/discriminants/tests/test_relative_distance.py
sklvq/distances/__init__.py
sklvq/distances/_adaptive_squared_euclidean.py
sklvq/distances/_base.py
sklvq/distances/_euclidean.py
sklvq/distances/_local_adaptive_squared_euclidean.py
sklvq/distances/_squared_euclidean.py
sklvq/distances/tests/__init__.py
sklvq/distances/tests/test_adaptive_squared_euclidean.py
sklvq/distances/tests/test_common.py
sklvq/distances/tests/test_euclidean.py
sklvq/distances/tests/test_local_adaptive_squared_euclidean.py
sklvq/distances/tests/test_squared_euclidean.py
sklvq/models/__init__.py
sklvq/models/_base.py
sklvq/models/_glvq.py
sklvq/models/_gmlvq.py
sklvq/models/_lgmlvq.py
sklvq/models/tests/__init__.py
sklvq/models/tests/test_common.py
sklvq/models/tests/test_glvq.py
sklvq/models/tests/test_gmlq.py
sklvq/models/tests/test_lgmlvq.py
sklvq/objectives/__init__.py
sklvq/objectives/_base.py
sklvq/objectives/_generalized_learning_objective.py
sklvq/objectives/tests/__init__.py
sklvq/solvers/__init__.py
sklvq/solvers/_adaptive_moment_estimation.py
sklvq/solvers/_base.py
sklvq/solvers/_broyden_fletcher_goldfarb_shanno.py
sklvq/solvers/_limited_memory_bfgs.py
sklvq/solvers/_steepest_gradient_descent.py
sklvq/solvers/_waypoint_gradient_descent.py
sklvq/solvers/tests/__init__.py
sklvq/solvers/tests/test_adaptive_moment_estimation.py
sklvq-0.1.2.dist-info/LICENSE
sklvq-0.1.2.dist-info/METADATA
sklvq-0.1.2.dist-info/WHEEL
sklvq-0.1.2.dist-info/top_level.txt
sklvq-0.1.2.dist-info/RECORD
